sqlanydb.py
sqlanydb-1.0.6.1.dist-info/top_level.txt
sqlanydb-1.0.6.1.dist-info/METADATA
sqlanydb-1.0.6.1.dist-info/DESCRIPTION.rst
sqlanydb-1.0.6.1.dist-info/metadata.json
sqlanydb-1.0.6.1.dist-info/WHEEL
sqlanydb-1.0.6.1.dist-info/RECORD
